{"inputs":[0],"name":"alaw2linear","op-struct":{"graph":{"edges":[[0,95,{"out-nr":0,"etype":"data","in-nr":0}],[1,97,{"out-nr":0,"etype":"data","in-nr":0}],[2,4,{"out-nr":0,"etype":"data","in-nr":0}],[4,99,{"out-nr":0,"etype":"data","in-nr":0}],[5,7,{"out-nr":0,"etype":"data","in-nr":0}],[7,101,{"out-nr":0,"etype":"data","in-nr":0}],[7,103,{"out-nr":1,"etype":"data","in-nr":0}],[7,105,{"out-nr":2,"etype":"data","in-nr":0}],[9,11,{"out-nr":0,"etype":"data","in-nr":0}],[11,109,{"out-nr":0,"etype":"data","in-nr":0}],[12,111,{"out-nr":0,"etype":"data","in-nr":0}],[13,15,{"out-nr":0,"etype":"data","in-nr":0}],[15,113,{"out-nr":0,"etype":"data","in-nr":0}],[15,115,{"out-nr":1,"etype":"data","in-nr":0}],[15,117,{"out-nr":2,"etype":"data","in-nr":0}],[17,19,{"out-nr":0,"etype":"data","in-nr":0}],[19,121,{"out-nr":0,"etype":"data","in-nr":0}],[20,123,{"out-nr":0,"etype":"data","in-nr":0}],[21,23,{"out-nr":0,"etype":"data","in-nr":0}],[23,125,{"out-nr":0,"etype":"data","in-nr":0}],[23,127,{"out-nr":1,"etype":"data","in-nr":0}],[23,129,{"out-nr":2,"etype":"data","in-nr":0}],[23,131,{"out-nr":3,"etype":"data","in-nr":0}],[25,27,{"out-nr":0,"etype":"data","in-nr":0}],[27,135,{"out-nr":0,"etype":"data","in-nr":0}],[29,31,{"out-nr":0,"etype":"data","in-nr":0}],[31,139,{"out-nr":0,"etype":"data","in-nr":0}],[33,35,{"out-nr":0,"etype":"data","in-nr":0}],[35,143,{"out-nr":0,"etype":"data","in-nr":0}],[36,145,{"out-nr":0,"etype":"data","in-nr":0}],[37,39,{"out-nr":0,"etype":"data","in-nr":0}],[39,147,{"out-nr":0,"etype":"data","in-nr":0}],[41,43,{"out-nr":0,"etype":"data","in-nr":0}],[43,151,{"out-nr":0,"etype":"data","in-nr":0}],[45,47,{"out-nr":0,"etype":"data","in-nr":0}],[47,155,{"out-nr":0,"etype":"data","in-nr":0}],[48,157,{"out-nr":0,"etype":"data","in-nr":0}],[49,51,{"out-nr":0,"etype":"data","in-nr":0}],[51,159,{"out-nr":0,"etype":"data","in-nr":0}],[52,54,{"out-nr":0,"etype":"data","in-nr":0}],[54,161,{"out-nr":0,"etype":"data","in-nr":0}],[55,57,{"out-nr":0,"etype":"data","in-nr":0}],[57,163,{"out-nr":0,"etype":"data","in-nr":0}],[57,165,{"out-nr":1,"etype":"data","in-nr":0}],[58,167,{"out-nr":0,"etype":"data","in-nr":0}],[59,61,{"out-nr":0,"etype":"data","in-nr":0}],[61,169,{"out-nr":0,"etype":"data","in-nr":0}],[63,65,{"out-nr":0,"etype":"data","in-nr":0}],[65,173,{"out-nr":0,"etype":"data","in-nr":0}],[67,69,{"out-nr":0,"etype":"data","in-nr":0}],[69,177,{"out-nr":0,"etype":"data","in-nr":0}],[70,72,{"out-nr":0,"etype":"data","in-nr":0}],[72,179,{"out-nr":0,"etype":"data","in-nr":0}],[73,0,{"out-nr":0,"etype":"data","in-nr":0}],[73,1,{"out-nr":1,"etype":"data","in-nr":0}],[73,12,{"out-nr":3,"etype":"data","in-nr":0}],[73,20,{"out-nr":5,"etype":"data","in-nr":0}],[73,36,{"out-nr":9,"etype":"data","in-nr":0}],[73,48,{"out-nr":12,"etype":"data","in-nr":0}],[73,58,{"out-nr":13,"etype":"data","in-nr":0}],[73,74,{"out-nr":0,"etype":"ctrl","in-nr":0}],[73,181,{"out-nr":16,"etype":"data","in-nr":0}],[73,182,{"out-nr":17,"etype":"data","in-nr":0}],[73,183,{"out-nr":18,"etype":"data","in-nr":0}],[73,184,{"out-nr":19,"etype":"data","in-nr":0}],[74,75,{"out-nr":0,"etype":"ctrl","in-nr":0}],[75,76,{"out-nr":0,"etype":"ctrl","in-nr":0}],[76,185,{"out-nr":0,"etype":"ctrl","in-nr":0}],[76,187,{"out-nr":1,"etype":"ctrl","in-nr":0}],[77,82,{"out-nr":0,"etype":"ctrl","in-nr":0}],[78,79,{"out-nr":0,"etype":"ctrl","in-nr":0}],[79,189,{"out-nr":0,"etype":"ctrl","in-nr":0}],[79,191,{"out-nr":1,"etype":"ctrl","in-nr":0}],[80,86,{"out-nr":0,"etype":"ctrl","in-nr":0}],[81,87,{"out-nr":0,"etype":"ctrl","in-nr":0}],[82,193,{"out-nr":1,"etype":"ctrl","in-nr":0}],[82,195,{"out-nr":0,"etype":"ctrl","in-nr":0}],[83,84,{"out-nr":0,"etype":"ctrl","in-nr":0}],[84,85,{"out-nr":0,"etype":"ctrl","in-nr":0}],[85,57,{"out-nr":0,"etype":"def","in-nr":0}],[85,90,{"out-nr":0,"etype":"ctrl","in-nr":0}],[86,85,{"out-nr":0,"etype":"ctrl","in-nr":1}],[87,88,{"out-nr":0,"etype":"ctrl","in-nr":0}],[88,89,{"out-nr":0,"etype":"ctrl","in-nr":0}],[89,85,{"out-nr":0,"etype":"ctrl","in-nr":2}],[90,197,{"out-nr":0,"etype":"ctrl","in-nr":0}],[90,199,{"out-nr":1,"etype":"ctrl","in-nr":0}],[91,93,{"out-nr":0,"etype":"ctrl","in-nr":0}],[92,72,{"out-nr":0,"etype":"def","in-nr":0}],[92,94,{"out-nr":0,"etype":"ctrl","in-nr":0}],[93,92,{"out-nr":0,"etype":"ctrl","in-nr":1}],[95,96,{"out-nr":0,"etype":"data","in-nr":0}],[96,2,{"out-nr":0,"etype":"data","in-nr":0}],[97,98,{"out-nr":0,"etype":"data","in-nr":0}],[98,2,{"out-nr":0,"etype":"data","in-nr":1}],[99,100,{"out-nr":0,"etype":"data","in-nr":0}],[100,5,{"out-nr":0,"etype":"data","in-nr":0}],[101,102,{"out-nr":0,"etype":"data","in-nr":0}],[102,9,{"out-nr":0,"etype":"data","in-nr":0}],[103,104,{"out-nr":0,"etype":"data","in-nr":0}],[104,17,{"out-nr":0,"etype":"data","in-nr":0}],[105,106,{"out-nr":0,"etype":"data","in-nr":0}],[106,59,{"out-nr":0,"etype":"data","in-nr":0}],[107,108,{"out-nr":0,"etype":"data","in-nr":0}],[108,9,{"out-nr":0,"etype":"data","in-nr":1}],[109,110,{"out-nr":0,"etype":"data","in-nr":0}],[110,13,{"out-nr":0,"etype":"data","in-nr":0}],[111,112,{"out-nr":0,"etype":"data","in-nr":0}],[112,13,{"out-nr":0,"etype":"data","in-nr":1}],[113,114,{"out-nr":0,"etype":"data","in-nr":0}],[114,37,{"out-nr":0,"etype":"data","in-nr":0}],[115,116,{"out-nr":0,"etype":"data","in-nr":0}],[116,41,{"out-nr":0,"etype":"data","in-nr":0}],[117,118,{"out-nr":0,"etype":"data","in-nr":0}],[118,45,{"out-nr":0,"etype":"data","in-nr":0}],[119,120,{"out-nr":0,"etype":"data","in-nr":0}],[120,17,{"out-nr":0,"etype":"data","in-nr":1}],[121,122,{"out-nr":0,"etype":"data","in-nr":0}],[122,21,{"out-nr":0,"etype":"data","in-nr":0}],[123,124,{"out-nr":0,"etype":"data","in-nr":0}],[124,21,{"out-nr":0,"etype":"data","in-nr":1}],[125,126,{"out-nr":0,"etype":"data","in-nr":0}],[126,25,{"out-nr":0,"etype":"data","in-nr":0}],[127,128,{"out-nr":0,"etype":"data","in-nr":0}],[128,29,{"out-nr":0,"etype":"data","in-nr":0}],[129,130,{"out-nr":0,"etype":"data","in-nr":0}],[130,33,{"out-nr":0,"etype":"data","in-nr":0}],[131,132,{"out-nr":0,"etype":"data","in-nr":0}],[132,49,{"out-nr":0,"etype":"data","in-nr":0}],[133,134,{"out-nr":0,"etype":"data","in-nr":0}],[134,25,{"out-nr":0,"etype":"data","in-nr":1}],[135,136,{"out-nr":0,"etype":"data","in-nr":0}],[136,76,{"out-nr":0,"etype":"data","in-nr":0}],[137,138,{"out-nr":0,"etype":"data","in-nr":0}],[138,29,{"out-nr":0,"etype":"data","in-nr":1}],[139,140,{"out-nr":0,"etype":"data","in-nr":0}],[140,79,{"out-nr":0,"etype":"data","in-nr":0}],[141,142,{"out-nr":0,"etype":"data","in-nr":0}],[142,33,{"out-nr":0,"etype":"data","in-nr":1}],[143,144,{"out-nr":0,"etype":"data","in-nr":0}],[144,82,{"out-nr":0,"etype":"data","in-nr":0}],[145,146,{"out-nr":0,"etype":"data","in-nr":0}],[146,37,{"out-nr":0,"etype":"data","in-nr":1}],[147,148,{"out-nr":0,"etype":"data","in-nr":0}],[148,55,{"out-nr":0,"etype":"data","in-nr":2}],[148,83,{"out-nr":0,"etype":"def","in-nr":0}],[149,150,{"out-nr":0,"etype":"data","in-nr":0}],[150,41,{"out-nr":0,"etype":"data","in-nr":1}],[151,152,{"out-nr":0,"etype":"data","in-nr":0}],[152,55,{"out-nr":0,"etype":"data","in-nr":1}],[152,80,{"out-nr":0,"etype":"def","in-nr":0}],[153,154,{"out-nr":0,"etype":"data","in-nr":0}],[154,45,{"out-nr":0,"etype":"data","in-nr":1}],[155,156,{"out-nr":0,"etype":"data","in-nr":0}],[156,52,{"out-nr":0,"etype":"data","in-nr":0}],[157,158,{"out-nr":0,"etype":"data","in-nr":0}],[158,49,{"out-nr":0,"etype":"data","in-nr":1}],[159,160,{"out-nr":0,"etype":"data","in-nr":0}],[160,52,{"out-nr":0,"etype":"data","in-nr":1}],[161,162,{"out-nr":0,"etype":"data","in-nr":0}],[162,55,{"out-nr":0,"etype":"data","in-nr":0}],[162,88,{"out-nr":0,"etype":"def","in-nr":0}],[163,164,{"out-nr":0,"etype":"data","in-nr":0}],[164,67,{"out-nr":0,"etype":"data","in-nr":1}],[165,166,{"out-nr":0,"etype":"data","in-nr":0}],[166,70,{"out-nr":0,"etype":"data","in-nr":0}],[166,91,{"out-nr":0,"etype":"def","in-nr":0}],[167,168,{"out-nr":0,"etype":"data","in-nr":0}],[168,59,{"out-nr":0,"etype":"data","in-nr":1}],[169,170,{"out-nr":0,"etype":"data","in-nr":0}],[170,63,{"out-nr":0,"etype":"data","in-nr":0}],[171,172,{"out-nr":0,"etype":"data","in-nr":0}],[172,63,{"out-nr":0,"etype":"data","in-nr":1}],[173,174,{"out-nr":0,"etype":"data","in-nr":0}],[174,90,{"out-nr":0,"etype":"data","in-nr":0}],[175,176,{"out-nr":0,"etype":"data","in-nr":0}],[176,67,{"out-nr":0,"etype":"data","in-nr":0}],[177,178,{"out-nr":0,"etype":"data","in-nr":0}],[178,70,{"out-nr":0,"etype":"data","in-nr":1}],[178,85,{"out-nr":0,"etype":"def","in-nr":0}],[179,180,{"out-nr":0,"etype":"data","in-nr":0}],[180,94,{"out-nr":0,"etype":"data","in-nr":0}],[181,107,{"out-nr":1,"etype":"data","in-nr":0}],[181,119,{"out-nr":0,"etype":"data","in-nr":0}],[182,133,{"out-nr":1,"etype":"data","in-nr":0}],[182,137,{"out-nr":0,"etype":"data","in-nr":0}],[183,141,{"out-nr":2,"etype":"data","in-nr":0}],[183,171,{"out-nr":1,"etype":"data","in-nr":0}],[183,175,{"out-nr":0,"etype":"data","in-nr":0}],[184,149,{"out-nr":1,"etype":"data","in-nr":0}],[184,153,{"out-nr":0,"etype":"data","in-nr":0}],[185,186,{"out-nr":0,"etype":"ctrl","in-nr":0}],[186,77,{"out-nr":0,"etype":"ctrl","in-nr":0}],[187,188,{"out-nr":0,"etype":"ctrl","in-nr":0}],[188,78,{"out-nr":0,"etype":"ctrl","in-nr":0}],[189,190,{"out-nr":0,"etype":"ctrl","in-nr":0}],[190,80,{"out-nr":0,"etype":"ctrl","in-nr":0}],[191,192,{"out-nr":0,"etype":"ctrl","in-nr":0}],[192,81,{"out-nr":0,"etype":"ctrl","in-nr":0}],[193,194,{"out-nr":0,"etype":"ctrl","in-nr":0}],[194,81,{"out-nr":0,"etype":"ctrl","in-nr":1}],[195,196,{"out-nr":0,"etype":"ctrl","in-nr":0}],[196,83,{"out-nr":0,"etype":"ctrl","in-nr":0}],[197,198,{"out-nr":0,"etype":"ctrl","in-nr":0}],[198,91,{"out-nr":0,"etype":"ctrl","in-nr":0}],[199,200,{"out-nr":0,"etype":"ctrl","in-nr":0}],[200,92,{"out-nr":0,"etype":"ctrl","in-nr":0}]],"nodes":[[0,{"id":0,"type":{"origin":"%a_val","dtype":"i8","ntype":"data"}}],[1,{"id":1,"type":{"origin":"%const.85","dtype":"85 i8","ntype":"data"}}],[2,{"id":2,"type":{"op":"i ^","ntype":"comp"}}],[4,{"id":4,"type":{"origin":"%xor","dtype":"i8","ntype":"data"}}],[5,{"id":5,"type":{"op":"zext","ntype":"comp"}}],[7,{"id":7,"type":{"origin":"%conv2","dtype":"i32","ntype":"data"}}],[9,{"id":9,"type":{"op":"i <<","ntype":"comp"}}],[11,{"id":11,"type":{"origin":"%and","dtype":"i32","ntype":"data"}}],[12,{"id":12,"type":{"origin":"%const.240","dtype":"240 i32","ntype":"data"}}],[13,{"id":13,"type":{"op":"i &&","ntype":"comp"}}],[15,{"id":15,"type":{"origin":"%shl","dtype":"i32","ntype":"data"}}],[17,{"id":17,"type":{"op":"i >>","ntype":"comp"}}],[19,{"id":19,"type":{"origin":"%and4","dtype":"i32","ntype":"data"}}],[20,{"id":20,"type":{"origin":"%const.7","dtype":"7 i32","ntype":"data"}}],[21,{"id":21,"type":{"op":"i &&","ntype":"comp"}}],[23,{"id":23,"type":{"origin":"%shr","dtype":"i32","ntype":"data"}}],[25,{"id":25,"type":{"op":"si <","ntype":"comp"}}],[27,{"id":27,"type":{"origin":"%Pivot","dtype":"i1","ntype":"data"}}],[29,{"id":29,"type":{"op":"i ==","ntype":"comp"}}],[31,{"id":31,"type":{"origin":"%SwitchLeaf2","dtype":"i1","ntype":"data"}}],[33,{"id":33,"type":{"op":"i ==","ntype":"comp"}}],[35,{"id":35,"type":{"origin":"%SwitchLeaf","dtype":"i1","ntype":"data"}}],[36,{"id":36,"type":{"origin":"%const.8","dtype":"8 i32","ntype":"data"}}],[37,{"id":37,"type":{"op":"i ||","ntype":"comp"}}],[39,{"id":39,"type":{"origin":"%add21","dtype":"i32","ntype":"data"}}],[41,{"id":41,"type":{"op":"i ||","ntype":"comp"}}],[43,{"id":43,"type":{"origin":"%add620","dtype":"i32","ntype":"data"}}],[45,{"id":45,"type":{"op":"i ||","ntype":"comp"}}],[47,{"id":47,"type":{"origin":"%add722","dtype":"i32","ntype":"data"}}],[48,{"id":48,"type":{"origin":"%const.-1","dtype":"-1 i32","ntype":"data"}}],[49,{"id":49,"type":{"op":"i +","ntype":"comp"}}],[51,{"id":51,"type":{"origin":"%sub","dtype":"i32","ntype":"data"}}],[52,{"id":52,"type":{"op":"i <<","ntype":"comp"}}],[54,{"id":54,"type":{"origin":"%shl8","dtype":"i32","ntype":"data"}}],[55,{"id":55,"type":{"ntype":"phi"}}],[57,{"id":57,"type":{"origin":"%t.0","dtype":"i32","ntype":"data"}}],[58,{"id":58,"type":{"origin":"%const.128","dtype":"128 i32","ntype":"data"}}],[59,{"id":59,"type":{"op":"i &&","ntype":"comp"}}],[61,{"id":61,"type":{"origin":"%and10","dtype":"i32","ntype":"data"}}],[63,{"id":63,"type":{"op":"i !=","ntype":"comp"}}],[65,{"id":65,"type":{"origin":"%tobool","dtype":"i1","ntype":"data"}}],[67,{"id":67,"type":{"op":"i -","ntype":"comp"}}],[69,{"id":69,"type":{"origin":"%sub11","dtype":"i32","ntype":"data"}}],[70,{"id":70,"type":{"ntype":"phi"}}],[72,{"id":72,"type":{"origin":"%cond","dtype":"i32","ntype":"data"}}],[73,{"id":73,"type":{"block-name":"entry","ntype":"lab"}}],[74,{"id":74,"type":{"op":"br","ntype":"ctrl"}}],[75,{"id":75,"type":{"block-name":"NodeBlock","ntype":"lab"}}],[76,{"id":76,"type":{"op":"cbr","ntype":"ctrl"}}],[77,{"id":77,"type":{"block-name":"LeafBlock","ntype":"lab"}}],[78,{"id":78,"type":{"block-name":"LeafBlock1","ntype":"lab"}}],[79,{"id":79,"type":{"op":"cbr","ntype":"ctrl"}}],[80,{"id":80,"type":{"block-name":"sw.bb5","ntype":"lab"}}],[81,{"id":81,"type":{"block-name":"NewDefault","ntype":"lab"}}],[82,{"id":82,"type":{"op":"cbr","ntype":"ctrl"}}],[83,{"id":83,"type":{"block-name":"sw.bb","ntype":"lab"}}],[84,{"id":84,"type":{"op":"br","ntype":"ctrl"}}],[85,{"id":85,"type":{"block-name":"sw.epilog","ntype":"lab"}}],[86,{"id":86,"type":{"op":"br","ntype":"ctrl"}}],[87,{"id":87,"type":{"op":"br","ntype":"ctrl"}}],[88,{"id":88,"type":{"block-name":"sw.default","ntype":"lab"}}],[89,{"id":89,"type":{"op":"br","ntype":"ctrl"}}],[90,{"id":90,"type":{"op":"cbr","ntype":"ctrl"}}],[91,{"id":91,"type":{"block-name":"sw.epilog.selecttrue","ntype":"lab"}}],[92,{"id":92,"type":{"block-name":"sw.epilog.selectcont","ntype":"lab"}}],[93,{"id":93,"type":{"op":"br","ntype":"ctrl"}}],[94,{"id":94,"type":{"op":"ret","ntype":"ctrl"}}],[95,{"id":95,"type":{"ntype":"copy"}}],[96,{"id":96,"type":{"origin":"%a_val.copy.1","dtype":"i8","ntype":"data"}}],[97,{"id":97,"type":{"ntype":"copy"}}],[98,{"id":98,"type":{"origin":"%const.85.copy.1","dtype":"i8","ntype":"data"}}],[99,{"id":99,"type":{"ntype":"copy"}}],[100,{"id":100,"type":{"origin":"%xor.copy.1","dtype":"i8","ntype":"data"}}],[101,{"id":101,"type":{"ntype":"copy"}}],[102,{"id":102,"type":{"origin":"%conv2.copy.1","dtype":"i32","ntype":"data"}}],[103,{"id":103,"type":{"ntype":"copy"}}],[104,{"id":104,"type":{"origin":"%conv2.copy.2","dtype":"i32","ntype":"data"}}],[105,{"id":105,"type":{"ntype":"copy"}}],[106,{"id":106,"type":{"origin":"%conv2.copy.3","dtype":"i32","ntype":"data"}}],[107,{"id":107,"type":{"ntype":"copy"}}],[108,{"id":108,"type":{"origin":"%const.4.copy.1","dtype":"i32","ntype":"data"}}],[109,{"id":109,"type":{"ntype":"copy"}}],[110,{"id":110,"type":{"origin":"%and.copy.1","dtype":"i32","ntype":"data"}}],[111,{"id":111,"type":{"ntype":"copy"}}],[112,{"id":112,"type":{"origin":"%const.240.copy.1","dtype":"i32","ntype":"data"}}],[113,{"id":113,"type":{"ntype":"copy"}}],[114,{"id":114,"type":{"origin":"%shl.copy.1","dtype":"i32","ntype":"data"}}],[115,{"id":115,"type":{"ntype":"copy"}}],[116,{"id":116,"type":{"origin":"%shl.copy.2","dtype":"i32","ntype":"data"}}],[117,{"id":117,"type":{"ntype":"copy"}}],[118,{"id":118,"type":{"origin":"%shl.copy.3","dtype":"i32","ntype":"data"}}],[119,{"id":119,"type":{"ntype":"copy"}}],[120,{"id":120,"type":{"origin":"%const.4.copy.2","dtype":"i32","ntype":"data"}}],[121,{"id":121,"type":{"ntype":"copy"}}],[122,{"id":122,"type":{"origin":"%and4.copy.1","dtype":"i32","ntype":"data"}}],[123,{"id":123,"type":{"ntype":"copy"}}],[124,{"id":124,"type":{"origin":"%const.7.copy.1","dtype":"i32","ntype":"data"}}],[125,{"id":125,"type":{"ntype":"copy"}}],[126,{"id":126,"type":{"origin":"%shr.copy.1","dtype":"i32","ntype":"data"}}],[127,{"id":127,"type":{"ntype":"copy"}}],[128,{"id":128,"type":{"origin":"%shr.copy.2","dtype":"i32","ntype":"data"}}],[129,{"id":129,"type":{"ntype":"copy"}}],[130,{"id":130,"type":{"origin":"%shr.copy.3","dtype":"i32","ntype":"data"}}],[131,{"id":131,"type":{"ntype":"copy"}}],[132,{"id":132,"type":{"origin":"%shr.copy.4","dtype":"i32","ntype":"data"}}],[133,{"id":133,"type":{"ntype":"copy"}}],[134,{"id":134,"type":{"origin":"%const.1.copy.1","dtype":"i32","ntype":"data"}}],[135,{"id":135,"type":{"ntype":"copy"}}],[136,{"id":136,"type":{"origin":"%Pivot.copy.1","dtype":"i1","ntype":"data"}}],[137,{"id":137,"type":{"ntype":"copy"}}],[138,{"id":138,"type":{"origin":"%const.1.copy.2","dtype":"i32","ntype":"data"}}],[139,{"id":139,"type":{"ntype":"copy"}}],[140,{"id":140,"type":{"origin":"%SwitchLeaf2.copy.1","dtype":"i1","ntype":"data"}}],[141,{"id":141,"type":{"ntype":"copy"}}],[142,{"id":142,"type":{"origin":"%const.0.copy.1","dtype":"i32","ntype":"data"}}],[143,{"id":143,"type":{"ntype":"copy"}}],[144,{"id":144,"type":{"origin":"%SwitchLeaf.copy.1","dtype":"i1","ntype":"data"}}],[145,{"id":145,"type":{"ntype":"copy"}}],[146,{"id":146,"type":{"origin":"%const.8.copy.1","dtype":"i32","ntype":"data"}}],[147,{"id":147,"type":{"ntype":"copy"}}],[148,{"id":148,"type":{"origin":"%add21.copy.1","dtype":"i32","ntype":"data"}}],[149,{"id":149,"type":{"ntype":"copy"}}],[150,{"id":150,"type":{"origin":"%const.264.copy.1","dtype":"i32","ntype":"data"}}],[151,{"id":151,"type":{"ntype":"copy"}}],[152,{"id":152,"type":{"origin":"%add620.copy.1","dtype":"i32","ntype":"data"}}],[153,{"id":153,"type":{"ntype":"copy"}}],[154,{"id":154,"type":{"origin":"%const.264.copy.2","dtype":"i32","ntype":"data"}}],[155,{"id":155,"type":{"ntype":"copy"}}],[156,{"id":156,"type":{"origin":"%add722.copy.1","dtype":"i32","ntype":"data"}}],[157,{"id":157,"type":{"ntype":"copy"}}],[158,{"id":158,"type":{"origin":"%const.-1.copy.1","dtype":"i32","ntype":"data"}}],[159,{"id":159,"type":{"ntype":"copy"}}],[160,{"id":160,"type":{"origin":"%sub.copy.1","dtype":"i32","ntype":"data"}}],[161,{"id":161,"type":{"ntype":"copy"}}],[162,{"id":162,"type":{"origin":"%shl8.copy.1","dtype":"i32","ntype":"data"}}],[163,{"id":163,"type":{"ntype":"copy"}}],[164,{"id":164,"type":{"origin":"%t.0.copy.1","dtype":"i32","ntype":"data"}}],[165,{"id":165,"type":{"ntype":"copy"}}],[166,{"id":166,"type":{"origin":"%t.0.copy.2","dtype":"i32","ntype":"data"}}],[167,{"id":167,"type":{"ntype":"copy"}}],[168,{"id":168,"type":{"origin":"%const.128.copy.1","dtype":"i32","ntype":"data"}}],[169,{"id":169,"type":{"ntype":"copy"}}],[170,{"id":170,"type":{"origin":"%and10.copy.1","dtype":"i32","ntype":"data"}}],[171,{"id":171,"type":{"ntype":"copy"}}],[172,{"id":172,"type":{"origin":"%const.0.copy.2","dtype":"i32","ntype":"data"}}],[173,{"id":173,"type":{"ntype":"copy"}}],[174,{"id":174,"type":{"origin":"%tobool.copy.1","dtype":"i1","ntype":"data"}}],[175,{"id":175,"type":{"ntype":"copy"}}],[176,{"id":176,"type":{"origin":"%const.0.copy.3","dtype":"i32","ntype":"data"}}],[177,{"id":177,"type":{"ntype":"copy"}}],[178,{"id":178,"type":{"origin":"%sub11.copy.1","dtype":"i32","ntype":"data"}}],[179,{"id":179,"type":{"ntype":"copy"}}],[180,{"id":180,"type":{"origin":"%cond.copy.1","dtype":"i32","ntype":"data"}}],[181,{"id":181,"type":{"origin":null,"dtype":"4","ntype":"data"}}],[182,{"id":182,"type":{"origin":null,"dtype":"1","ntype":"data"}}],[183,{"id":183,"type":{"origin":null,"dtype":"0","ntype":"data"}}],[184,{"id":184,"type":{"origin":null,"dtype":"264","ntype":"data"}}],[185,{"id":185,"type":{"block-name":"bb0","ntype":"lab"}}],[186,{"id":186,"type":{"op":"br","ntype":"ctrl"}}],[187,{"id":187,"type":{"block-name":"bb1","ntype":"lab"}}],[188,{"id":188,"type":{"op":"br","ntype":"ctrl"}}],[189,{"id":189,"type":{"block-name":"bb2","ntype":"lab"}}],[190,{"id":190,"type":{"op":"br","ntype":"ctrl"}}],[191,{"id":191,"type":{"block-name":"bb3","ntype":"lab"}}],[192,{"id":192,"type":{"op":"br","ntype":"ctrl"}}],[193,{"id":193,"type":{"block-name":"bb4","ntype":"lab"}}],[194,{"id":194,"type":{"op":"br","ntype":"ctrl"}}],[195,{"id":195,"type":{"block-name":"bb5","ntype":"lab"}}],[196,{"id":196,"type":{"op":"br","ntype":"ctrl"}}],[197,{"id":197,"type":{"block-name":"bb6","ntype":"lab"}}],[198,{"id":198,"type":{"op":"br","ntype":"ctrl"}}],[199,{"id":199,"type":{"block-name":"bb7","ntype":"lab"}}],[200,{"id":200,"type":{"op":"br","ntype":"ctrl"}}]]},"entry-block-node":73,"constraints":[]},"bb-exec-freqs":[["entry",16384],["NodeBlock",16384],["LeafBlock",6144],["LeafBlock1",10240],["sw.bb5",5120],["NewDefault",8960],["sw.bb",2304],["sw.epilog",16384],["sw.default",8960],["sw.epilog.selecttrue",10240],["sw.epilog.selectcont",16384],["bb0",16384],["bb1",16384],["bb2",10240],["bb3",10240],["bb4",6144],["bb5",6144],["bb6",16384],["bb7",16384]]}